client
cloud
connect
datasherlock
validate
