Metadata-Version: 2.1
Name: datasherlock
Version: 0.0.27
Summary: datasherlock
Home-page: http://datasherlock.io
Author: datasherlock
Author-email: founder@datasherlock.io
License: UNKNOWN
Keywords: datasherlock
Platform: UNKNOWN
Classifier: Programming Language :: Python :: 3
Classifier: License :: OSI Approved :: MIT License
Classifier: Operating System :: OS Independent
Classifier: Intended Audience :: Developers
Classifier: Topic :: Software Development :: Libraries :: Python Modules
Provides-Extra: bigquery
Provides-Extra: databricks
Provides-Extra: mysql
Provides-Extra: postgres
Provides-Extra: redshift
Provides-Extra: snowflake
